{
 "actions": [],
 "allow_rename": 1,
 "creation": "2024-06-28 13:50:37.722379",
 "doctype": "DocType",
 "editable_grid": 1,
 "engine": "InnoDB",
 "field_order": [
  "satuan_tugas",
  "nama_satuan_tugas",
  "instansi",
  "tingkat_satuan_tugas",
  "sk_tugas",
  "tmt_sk_tugas",
  "terpasang_papan__plang",
  "tersedia_formulir"
 ],
 "fields": [
  {
   "fieldname": "satuan_tugas",
   "fieldtype": "Select",
   "in_list_view": 1,
   "label": "Satuan Tugas",
   "options": "Kegiatan Keaagamaan\nLiterasi Sekolah\nPenanggulangan Tindak Kekerasan di Sekolah\nPenerimaan Peserta Didik Baru\nPengenalan Lingkungan Sekolah\nPenyelenggara Komite Sekolah\nPenyelenggara Ujian Nasional\nTim Bos Sekolah\nTim Pendataan Sekolah",
   "reqd": 1
  },
  {
   "fieldname": "nama_satuan_tugas",
   "fieldtype": "Data",
   "in_list_view": 1,
   "label": "Nama Satuan Tugas",
   "reqd": 1
  },
  {
   "fieldname": "instansi",
   "fieldtype": "Data",
   "in_list_view": 1,
   "label": "Instansi",
   "reqd": 1
  },
  {
   "fieldname": "tingkat_satuan_tugas",
   "fieldtype": "Select",
   "in_list_view": 1,
   "label": "Tingkat Satuan Tugas",
   "options": "Lokal / Satuan Pendidikan\nDaerah",
   "reqd": 1
  },
  {
   "fieldname": "sk_tugas",
   "fieldtype": "Data",
   "in_list_view": 1,
   "label": "SK Tugas",
   "reqd": 1
  },
  {
   "fieldname": "tmt_sk_tugas",
   "fieldtype": "Date",
   "in_list_view": 1,
   "label": "TMT SK Tugas",
   "reqd": 1
  },
  {
   "fieldname": "terpasang_papan__plang",
   "fieldtype": "Select",
   "in_list_view": 1,
   "label": "Terpasang Papan / Plang",
   "options": "Ya\nTidak",
   "reqd": 1
  },
  {
   "fieldname": "tersedia_formulir",
   "fieldtype": "Select",
   "in_list_view": 1,
   "label": "Tersedia Formulir",
   "options": "Ya\nTidak",
   "reqd": 1
  }
 ],
 "index_web_pages_for_search": 1,
 "istable": 1,
 "links": [],
 "modified": "2024-06-28 14:06:11.162894",
 "modified_by": "Administrator",
 "module": "Akademik",
 "name": "CT Kepanitiaan Sekolah",
 "owner": "Administrator",
 "permissions": [],
 "sort_field": "creation",
 "sort_order": "DESC",
 "states": []
}